[
  {
    "@context": "http://schema.org",
    "@type": [
      "Event"
    ],
    "name": "\"Gaumenschmeichler und Magentratzer\" mit Harfe oder Zither",
    "eventStatus": "http://schema.org/EventScheduled",
    "organizer": {
      "@type": "Organization",
      "name": "",
      "employee": {
        "@type": "Person",
        "givenName": "9ers",
        "familyName": "Restaurant - Lounge - Bar"
      },
      "address": {
        "@type": "PostalAddress",
        "streetAddress": "Möserer Dorfstr. 2",
        "addressLocality": "Mösern",
        "postalCode": "6100",
        "addressCountry": "AT",
        "telephone": "+4352124747",
        "email": "info@inntalerhof.com",
        "url": "http://www.inntalerhof.com"
      }
    },
    "location": {
      "@type": "Place",
      "name": "",
      "address": {
        "@type": "PostalAddress",
        "streetAddress": "Möserer Dorfstr. 2",
        "addressLocality": "Mösern",
        "postalCode": "6100",
        "addressCountry": "AT",
        "telephone": "+4352124747",
        "email": "info@inntalerhof.com",
        "url": "http://www.inntalerhof.com"
      }
    },
    "description": "Festliches 5-Gang-Menü „Gaumenschmeichler \u0026 Magentratzer“ mit Tiroler Klängen von Harfe oder Zither ab 19:00 Uhr im Restaurant \"9ers\" im Hotel Inntalerhof. Reservierung erbeten unter: Tel. 05212 4747 Preis pro Person € 41,- oder a la carte. ",
    "image": [
      {
        "@type": "ImageObject",
        "url": "http://resc.deskline.net/images/SEE/1/2c306217-a0bb-43da-a356-93ba9068d079/99/image.jpg",
        "caption": "Pianobar"
      }
    ],
    "startDate": "2017-01-18T19:00:00",
    "endDate": "2017-01-18"
  },
  {
    "@context": "http://schema.org",
    "@type": [
      "Event"
    ],
    "name": "\"Gaumenschmeichler und Magentratzer\" mit Harfe oder Zither",
    "eventStatus": "http://schema.org/EventScheduled",
    "organizer": {
      "@type": "Organization",
      "name": "",
      "employee": {
        "@type": "Person",
        "givenName": "9ers",
        "familyName": "Restaurant - Lounge - Bar"
      },
      "address": {
        "@type": "PostalAddress",
        "streetAddress": "Möserer Dorfstr. 2",
        "addressLocality": "Mösern",
        "postalCode": "6100",
        "addressCountry": "AT",
        "telephone": "+4352124747",
        "email": "info@inntalerhof.com",
        "url": "http://www.inntalerhof.com"
      }
    },
    "location": {
      "@type": "Place",
      "name": "",
      "address": {
        "@type": "PostalAddress",
        "streetAddress": "Möserer Dorfstr. 2",
        "addressLocality": "Mösern",
        "postalCode": "6100",
        "addressCountry": "AT",
        "telephone": "+4352124747",
        "email": "info@inntalerhof.com",
        "url": "http://www.inntalerhof.com"
      }
    },
    "description": "Festliches 5-Gang-Menü „Gaumenschmeichler \u0026 Magentratzer“ mit Tiroler Klängen von Harfe oder Zither ab 19:00 Uhr im Restaurant \"9ers\" im Hotel Inntalerhof. Reservierung erbeten unter: Tel. 05212 4747 Preis pro Person € 41,- oder a la carte. ",
    "image": [
      {
        "@type": "ImageObject",
        "url": "http://resc.deskline.net/images/SEE/1/2c306217-a0bb-43da-a356-93ba9068d079/99/image.jpg",
        "caption": "Pianobar"
      }
    ],
    "startDate": "2017-01-24T19:00:00",
    "endDate": "2017-01-24"
  },
  {
    "@context": "http://schema.org",
    "@type": [
      "Event"
    ],
    "name": "\"Gaumenschmeichler und Magentratzer\" mit Harfe oder Zither",
    "eventStatus": "http://schema.org/EventScheduled",
    "organizer": {
      "@type": "Organization",
      "name": "",
      "employee": {
        "@type": "Person",
        "givenName": "9ers",
        "familyName": "Restaurant - Lounge - Bar"
      },
      "address": {
        "@type": "PostalAddress",
        "streetAddress": "Möserer Dorfstr. 2",
        "addressLocality": "Mösern",
        "postalCode": "6100",
        "addressCountry": "AT",
        "telephone": "+4352124747",
        "email": "info@inntalerhof.com",
        "url": "http://www.inntalerhof.com"
      }
    },
    "location": {
      "@type": "Place",
      "name": "",
      "address": {
        "@type": "PostalAddress",
        "streetAddress": "Möserer Dorfstr. 2",
        "addressLocality": "Mösern",
        "postalCode": "6100",
        "addressCountry": "AT",
        "telephone": "+4352124747",
        "email": "info@inntalerhof.com",
        "url": "http://www.inntalerhof.com"
      }
    },
    "description": "Festliches 5-Gang-Menü „Gaumenschmeichler \u0026 Magentratzer“ mit Tiroler Klängen von Harfe oder Zither ab 19:00 Uhr im Restaurant \"9ers\" im Hotel Inntalerhof. Reservierung erbeten unter: Tel. 05212 4747 Preis pro Person € 41,- oder a la carte. ",
    "image": [
      {
        "@type": "ImageObject",
        "url": "http://resc.deskline.net/images/SEE/1/2c306217-a0bb-43da-a356-93ba9068d079/99/image.jpg",
        "caption": "Pianobar"
      }
    ],
    "startDate": "2017-01-31T19:00:00",
    "endDate": "2017-01-31"
  },
  {
    "@context": "http://schema.org",
    "@type": [
      "Event"
    ],
    "name": "\"Gaumenschmeichler und Magentratzer\" mit Harfe oder Zither",
    "eventStatus": "http://schema.org/EventScheduled",
    "organizer": {
      "@type": "Organization",
      "name": "",
      "employee": {
        "@type": "Person",
        "givenName": "9ers",
        "familyName": "Restaurant - Lounge - Bar"
      },
      "address": {
        "@type": "PostalAddress",
        "streetAddress": "Möserer Dorfstr. 2",
        "addressLocality": "Mösern",
        "postalCode": "6100",
        "addressCountry": "AT",
        "telephone": "+4352124747",
        "email": "info@inntalerhof.com",
        "url": "http://www.inntalerhof.com"
      }
    },
    "location": {
      "@type": "Place",
      "name": "",
      "address": {
        "@type": "PostalAddress",
        "streetAddress": "Möserer Dorfstr. 2",
        "addressLocality": "Mösern",
        "postalCode": "6100",
        "addressCountry": "AT",
        "telephone": "+4352124747",
        "email": "info@inntalerhof.com",
        "url": "http://www.inntalerhof.com"
      }
    },
    "description": "Festliches 5-Gang-Menü „Gaumenschmeichler \u0026 Magentratzer“ mit Tiroler Klängen von Harfe oder Zither ab 19:00 Uhr im Restaurant \"9ers\" im Hotel Inntalerhof. Reservierung erbeten unter: Tel. 05212 4747 Preis pro Person € 41,- oder a la carte. ",
    "image": [
      {
        "@type": "ImageObject",
        "url": "http://resc.deskline.net/images/SEE/1/2c306217-a0bb-43da-a356-93ba9068d079/99/image.jpg",
        "caption": "Pianobar"
      }
    ],
    "startDate": "2017-02-07T19:00:00",
    "endDate": "2017-02-07"
  },
  {
    "@context": "http://schema.org",
    "@type": [
      "Event"
    ],
    "name": "\"Gaumenschmeichler und Magentratzer\" mit Harfe oder Zither",
    "eventStatus": "http://schema.org/EventScheduled",
    "organizer": {
      "@type": "Organization",
      "name": "",
      "employee": {
        "@type": "Person",
        "givenName": "9ers",
        "familyName": "Restaurant - Lounge - Bar"
      },
      "address": {
        "@type": "PostalAddress",
        "streetAddress": "Möserer Dorfstr. 2",
        "addressLocality": "Mösern",
        "postalCode": "6100",
        "addressCountry": "AT",
        "telephone": "+4352124747",
        "email": "info@inntalerhof.com",
        "url": "http://www.inntalerhof.com"
      }
    },
    "location": {
      "@type": "Place",
      "name": "",
      "address": {
        "@type": "PostalAddress",
        "streetAddress": "Möserer Dorfstr. 2",
        "addressLocality": "Mösern",
        "postalCode": "6100",
        "addressCountry": "AT",
        "telephone": "+4352124747",
        "email": "info@inntalerhof.com",
        "url": "http://www.inntalerhof.com"
      }
    },
    "description": "Festliches 5-Gang-Menü „Gaumenschmeichler \u0026 Magentratzer“ mit Tiroler Klängen von Harfe oder Zither ab 19:00 Uhr im Restaurant \"9ers\" im Hotel Inntalerhof. Reservierung erbeten unter: Tel. 05212 4747 Preis pro Person € 41,- oder a la carte. ",
    "image": [
      {
        "@type": "ImageObject",
        "url": "http://resc.deskline.net/images/SEE/1/2c306217-a0bb-43da-a356-93ba9068d079/99/image.jpg",
        "caption": "Pianobar"
      }
    ],
    "startDate": "2017-02-14T19:00:00",
    "endDate": "2017-02-14"
  },
  {
    "@context": "http://schema.org",
    "@type": [
      "Event"
    ],
    "name": "\"Gaumenschmeichler und Magentratzer\" mit Harfe oder Zither",
    "eventStatus": "http://schema.org/EventScheduled",
    "organizer": {
      "@type": "Organization",
      "name": "",
      "employee": {
        "@type": "Person",
        "givenName": "9ers",
        "familyName": "Restaurant - Lounge - Bar"
      },
      "address": {
        "@type": "PostalAddress",
        "streetAddress": "Möserer Dorfstr. 2",
        "addressLocality": "Mösern",
        "postalCode": "6100",
        "addressCountry": "AT",
        "telephone": "+4352124747",
        "email": "info@inntalerhof.com",
        "url": "http://www.inntalerhof.com"
      }
    },
    "location": {
      "@type": "Place",
      "name": "",
      "address": {
        "@type": "PostalAddress",
        "streetAddress": "Möserer Dorfstr. 2",
        "addressLocality": "Mösern",
        "postalCode": "6100",
        "addressCountry": "AT",
        "telephone": "+4352124747",
        "email": "info@inntalerhof.com",
        "url": "http://www.inntalerhof.com"
      }
    },
    "description": "Festliches 5-Gang-Menü „Gaumenschmeichler \u0026 Magentratzer“ mit Tiroler Klängen von Harfe oder Zither ab 19:00 Uhr im Restaurant \"9ers\" im Hotel Inntalerhof. Reservierung erbeten unter: Tel. 05212 4747 Preis pro Person € 41,- oder a la carte. ",
    "image": [
      {
        "@type": "ImageObject",
        "url": "http://resc.deskline.net/images/SEE/1/2c306217-a0bb-43da-a356-93ba9068d079/99/image.jpg",
        "caption": "Pianobar"
      }
    ],
    "startDate": "2017-02-21T19:00:00",
    "endDate": "2017-02-21"
  },
  {
    "@context": "http://schema.org",
    "@type": [
      "Event"
    ],
    "name": "\"Gaumenschmeichler und Magentratzer\" mit Harfe oder Zither",
    "eventStatus": "http://schema.org/EventScheduled",
    "organizer": {
      "@type": "Organization",
      "name": "",
      "employee": {
        "@type": "Person",
        "givenName": "9ers",
        "familyName": "Restaurant - Lounge - Bar"
      },
      "address": {
        "@type": "PostalAddress",
        "streetAddress": "Möserer Dorfstr. 2",
        "addressLocality": "Mösern",
        "postalCode": "6100",
        "addressCountry": "AT",
        "telephone": "+4352124747",
        "email": "info@inntalerhof.com",
        "url": "http://www.inntalerhof.com"
      }
    },
    "location": {
      "@type": "Place",
      "name": "",
      "address": {
        "@type": "PostalAddress",
        "streetAddress": "Möserer Dorfstr. 2",
        "addressLocality": "Mösern",
        "postalCode": "6100",
        "addressCountry": "AT",
        "telephone": "+4352124747",
        "email": "info@inntalerhof.com",
        "url": "http://www.inntalerhof.com"
      }
    },
    "description": "Festliches 5-Gang-Menü „Gaumenschmeichler \u0026 Magentratzer“ mit Tiroler Klängen von Harfe oder Zither ab 19:00 Uhr im Restaurant \"9ers\" im Hotel Inntalerhof. Reservierung erbeten unter: Tel. 05212 4747 Preis pro Person € 41,- oder a la carte. ",
    "image": [
      {
        "@type": "ImageObject",
        "url": "http://resc.deskline.net/images/SEE/1/2c306217-a0bb-43da-a356-93ba9068d079/99/image.jpg",
        "caption": "Pianobar"
      }
    ],
    "startDate": "2017-02-28T19:00:00",
    "endDate": "2017-02-28"
  },
  {
    "@context": "http://schema.org",
    "@type": [
      "Event"
    ],
    "name": "\"Gaumenschmeichler und Magentratzer\" mit Harfe oder Zither",
    "eventStatus": "http://schema.org/EventScheduled",
    "organizer": {
      "@type": "Organization",
      "name": "",
      "employee": {
        "@type": "Person",
        "givenName": "9ers",
        "familyName": "Restaurant - Lounge - Bar"
      },
      "address": {
        "@type": "PostalAddress",
        "streetAddress": "Möserer Dorfstr. 2",
        "addressLocality": "Mösern",
        "postalCode": "6100",
        "addressCountry": "AT",
        "telephone": "+4352124747",
        "email": "info@inntalerhof.com",
        "url": "http://www.inntalerhof.com"
      }
    },
    "location": {
      "@type": "Place",
      "name": "",
      "address": {
        "@type": "PostalAddress",
        "streetAddress": "Möserer Dorfstr. 2",
        "addressLocality": "Mösern",
        "postalCode": "6100",
        "addressCountry": "AT",
        "telephone": "+4352124747",
        "email": "info@inntalerhof.com",
        "url": "http://www.inntalerhof.com"
      }
    },
    "description": "Festliches 5-Gang-Menü „Gaumenschmeichler \u0026 Magentratzer“ mit Tiroler Klängen von Harfe oder Zither ab 19:00 Uhr im Restaurant \"9ers\" im Hotel Inntalerhof. Reservierung erbeten unter: Tel. 05212 4747 Preis pro Person € 41,- oder a la carte. ",
    "image": [
      {
        "@type": "ImageObject",
        "url": "http://resc.deskline.net/images/SEE/1/2c306217-a0bb-43da-a356-93ba9068d079/99/image.jpg",
        "caption": "Pianobar"
      }
    ],
    "startDate": "2017-03-07T19:00:00",
    "endDate": "2017-03-07"
  },
  {
    "@context": "http://schema.org",
    "@type": [
      "Event"
    ],
    "name": "\"Gaumenschmeichler und Magentratzer\" mit Harfe oder Zither",
    "eventStatus": "http://schema.org/EventScheduled",
    "organizer": {
      "@type": "Organization",
      "name": "",
      "employee": {
        "@type": "Person",
        "givenName": "9ers",
        "familyName": "Restaurant - Lounge - Bar"
      },
      "address": {
        "@type": "PostalAddress",
        "streetAddress": "Möserer Dorfstr. 2",
        "addressLocality": "Mösern",
        "postalCode": "6100",
        "addressCountry": "AT",
        "telephone": "+4352124747",
        "email": "info@inntalerhof.com",
        "url": "http://www.inntalerhof.com"
      }
    },
    "location": {
      "@type": "Place",
      "name": "",
      "address": {
        "@type": "PostalAddress",
        "streetAddress": "Möserer Dorfstr. 2",
        "addressLocality": "Mösern",
        "postalCode": "6100",
        "addressCountry": "AT",
        "telephone": "+4352124747",
        "email": "info@inntalerhof.com",
        "url": "http://www.inntalerhof.com"
      }
    },
    "description": "Festliches 5-Gang-Menü „Gaumenschmeichler \u0026 Magentratzer“ mit Tiroler Klängen von Harfe oder Zither ab 19:00 Uhr im Restaurant \"9ers\" im Hotel Inntalerhof. Reservierung erbeten unter: Tel. 05212 4747 Preis pro Person € 41,- oder a la carte. ",
    "image": [
      {
        "@type": "ImageObject",
        "url": "http://resc.deskline.net/images/SEE/1/2c306217-a0bb-43da-a356-93ba9068d079/99/image.jpg",
        "caption": "Pianobar"
      }
    ],
    "startDate": "2017-03-14T19:00:00",
    "endDate": "2017-03-14"
  },
  {
    "@context": "http://schema.org",
    "@type": [
      "Event"
    ],
    "name": "\"Gaumenschmeichler und Magentratzer\" mit Harfe oder Zither",
    "eventStatus": "http://schema.org/EventScheduled",
    "organizer": {
      "@type": "Organization",
      "name": "",
      "employee": {
        "@type": "Person",
        "givenName": "9ers",
        "familyName": "Restaurant - Lounge - Bar"
      },
      "address": {
        "@type": "PostalAddress",
        "streetAddress": "Möserer Dorfstr. 2",
        "addressLocality": "Mösern",
        "postalCode": "6100",
        "addressCountry": "AT",
        "telephone": "+4352124747",
        "email": "info@inntalerhof.com",
        "url": "http://www.inntalerhof.com"
      }
    },
    "location": {
      "@type": "Place",
      "name": "",
      "address": {
        "@type": "PostalAddress",
        "streetAddress": "Möserer Dorfstr. 2",
        "addressLocality": "Mösern",
        "postalCode": "6100",
        "addressCountry": "AT",
        "telephone": "+4352124747",
        "email": "info@inntalerhof.com",
        "url": "http://www.inntalerhof.com"
      }
    },
    "description": "Festliches 5-Gang-Menü „Gaumenschmeichler \u0026 Magentratzer“ mit Tiroler Klängen von Harfe oder Zither ab 19:00 Uhr im Restaurant \"9ers\" im Hotel Inntalerhof. Reservierung erbeten unter: Tel. 05212 4747 Preis pro Person € 41,- oder a la carte. ",
    "image": [
      {
        "@type": "ImageObject",
        "url": "http://resc.deskline.net/images/SEE/1/2c306217-a0bb-43da-a356-93ba9068d079/99/image.jpg",
        "caption": "Pianobar"
      }
    ],
    "startDate": "2017-03-21T19:00:00",
    "endDate": "2017-03-21"
  },
  {
    "@context": "http://schema.org",
    "@type": [
      "Event"
    ],
    "name": "\"Gaumenschmeichler und Magentratzer\" mit Harfe oder Zither",
    "eventStatus": "http://schema.org/EventScheduled",
    "organizer": {
      "@type": "Organization",
      "name": "",
      "employee": {
        "@type": "Person",
        "givenName": "9ers",
        "familyName": "Restaurant - Lounge - Bar"
      },
      "address": {
        "@type": "PostalAddress",
        "streetAddress": "Möserer Dorfstr. 2",
        "addressLocality": "Mösern",
        "postalCode": "6100",
        "addressCountry": "AT",
        "telephone": "+4352124747",
        "email": "info@inntalerhof.com",
        "url": "http://www.inntalerhof.com"
      }
    },
    "location": {
      "@type": "Place",
      "name": "",
      "address": {
        "@type": "PostalAddress",
        "streetAddress": "Möserer Dorfstr. 2",
        "addressLocality": "Mösern",
        "postalCode": "6100",
        "addressCountry": "AT",
        "telephone": "+4352124747",
        "email": "info@inntalerhof.com",
        "url": "http://www.inntalerhof.com"
      }
    },
    "description": "Festliches 5-Gang-Menü „Gaumenschmeichler \u0026 Magentratzer“ mit Tiroler Klängen von Harfe oder Zither ab 19:00 Uhr im Restaurant \"9ers\" im Hotel Inntalerhof. Reservierung erbeten unter: Tel. 05212 4747 Preis pro Person € 41,- oder a la carte. ",
    "image": [
      {
        "@type": "ImageObject",
        "url": "http://resc.deskline.net/images/SEE/1/2c306217-a0bb-43da-a356-93ba9068d079/99/image.jpg",
        "caption": "Pianobar"
      }
    ],
    "startDate": "2017-03-28T19:00:00",
    "endDate": "2017-03-28"
  },
  {
    "@context": "http://schema.org",
    "@type": [
      "Event"
    ],
    "name": "\"Gaumenschmeichler und Magentratzer\" mit Harfe oder Zither",
    "eventStatus": "http://schema.org/EventScheduled",
    "organizer": {
      "@type": "Organization",
      "name": "",
      "employee": {
        "@type": "Person",
        "givenName": "9ers",
        "familyName": "Restaurant - Lounge - Bar"
      },
      "address": {
        "@type": "PostalAddress",
        "streetAddress": "Möserer Dorfstr. 2",
        "addressLocality": "Mösern",
        "postalCode": "6100",
        "addressCountry": "AT",
        "telephone": "+4352124747",
        "email": "info@inntalerhof.com",
        "url": "http://www.inntalerhof.com"
      }
    },
    "location": {
      "@type": "Place",
      "name": "",
      "address": {
        "@type": "PostalAddress",
        "streetAddress": "Möserer Dorfstr. 2",
        "addressLocality": "Mösern",
        "postalCode": "6100",
        "addressCountry": "AT",
        "telephone": "+4352124747",
        "email": "info@inntalerhof.com",
        "url": "http://www.inntalerhof.com"
      }
    },
    "description": "Festliches 5-Gang-Menü „Gaumenschmeichler \u0026 Magentratzer“ mit Tiroler Klängen von Harfe oder Zither ab 19:00 Uhr im Restaurant \"9ers\" im Hotel Inntalerhof. Reservierung erbeten unter: Tel. 05212 4747 Preis pro Person € 41,- oder a la carte. ",
    "image": [
      {
        "@type": "ImageObject",
        "url": "http://resc.deskline.net/images/SEE/1/2c306217-a0bb-43da-a356-93ba9068d079/99/image.jpg",
        "caption": "Pianobar"
      }
    ],
    "startDate": "2017-04-04T19:00:00",
    "endDate": "2017-04-04"
  },
  {
    "@context": "http://schema.org",
    "@type": [
      "Event"
    ],
    "name": "\"Gaumenschmeichler und Magentratzer\" mit Harfe oder Zither",
    "eventStatus": "http://schema.org/EventScheduled",
    "organizer": {
      "@type": "Organization",
      "name": "",
      "employee": {
        "@type": "Person",
        "givenName": "9ers",
        "familyName": "Restaurant - Lounge - Bar"
      },
      "address": {
        "@type": "PostalAddress",
        "streetAddress": "Möserer Dorfstr. 2",
        "addressLocality": "Mösern",
        "postalCode": "6100",
        "addressCountry": "AT",
        "telephone": "+4352124747",
        "email": "info@inntalerhof.com",
        "url": "http://www.inntalerhof.com"
      }
    },
    "location": {
      "@type": "Place",
      "name": "",
      "address": {
        "@type": "PostalAddress",
        "streetAddress": "Möserer Dorfstr. 2",
        "addressLocality": "Mösern",
        "postalCode": "6100",
        "addressCountry": "AT",
        "telephone": "+4352124747",
        "email": "info@inntalerhof.com",
        "url": "http://www.inntalerhof.com"
      }
    },
    "description": "Festliches 5-Gang-Menü „Gaumenschmeichler \u0026 Magentratzer“ mit Tiroler Klängen von Harfe oder Zither ab 19:00 Uhr im Restaurant \"9ers\" im Hotel Inntalerhof. Reservierung erbeten unter: Tel. 05212 4747 Preis pro Person € 41,- oder a la carte. ",
    "image": [
      {
        "@type": "ImageObject",
        "url": "http://resc.deskline.net/images/SEE/1/2c306217-a0bb-43da-a356-93ba9068d079/99/image.jpg",
        "caption": "Pianobar"
      }
    ],
    "startDate": "2017-04-11T19:00:00",
    "endDate": "2017-04-11"
  },
  {
    "@context": "http://schema.org",
    "@type": [
      "Event"
    ],
    "name": "\"Gaumenschmeichler und Magentratzer\" mit Harfe oder Zither",
    "eventStatus": "http://schema.org/EventScheduled",
    "organizer": {
      "@type": "Organization",
      "name": "",
      "employee": {
        "@type": "Person",
        "givenName": "9ers",
        "familyName": "Restaurant - Lounge - Bar"
      },
      "address": {
        "@type": "PostalAddress",
        "streetAddress": "Möserer Dorfstr. 2",
        "addressLocality": "Mösern",
        "postalCode": "6100",
        "addressCountry": "AT",
        "telephone": "+4352124747",
        "email": "info@inntalerhof.com",
        "url": "http://www.inntalerhof.com"
      }
    },
    "location": {
      "@type": "Place",
      "name": "",
      "address": {
        "@type": "PostalAddress",
        "streetAddress": "Möserer Dorfstr. 2",
        "addressLocality": "Mösern",
        "postalCode": "6100",
        "addressCountry": "AT",
        "telephone": "+4352124747",
        "email": "info@inntalerhof.com",
        "url": "http://www.inntalerhof.com"
      }
    },
    "description": "Festliches 5-Gang-Menü „Gaumenschmeichler \u0026 Magentratzer“ mit Tiroler Klängen von Harfe oder Zither ab 19:00 Uhr im Restaurant \"9ers\" im Hotel Inntalerhof. Reservierung erbeten unter: Tel. 05212 4747 Preis pro Person € 41,- oder a la carte. ",
    "image": [
      {
        "@type": "ImageObject",
        "url": "http://resc.deskline.net/images/SEE/1/2c306217-a0bb-43da-a356-93ba9068d079/99/image.jpg",
        "caption": "Pianobar"
      }
    ],
    "startDate": "2017-04-17T19:00:00",
    "endDate": "2017-04-17"
  }
]