{
  "@context": "http://schema.org",
  "@type": [
    "LodgingBusiness"
  ],
  "url": [
    "http://www.apartment-leutasch.at"
  ],
  "address": {
    "@type": "PostalAddress",
    "name": "Haus am Burggraben",
    "streetAddress": "Burggraben 260",
    "addressLocality": "Leutasch",
    "postalCode": "6105",
    "addressCountry": "AT",
    "telephone": "(0043) 664 8936323",
    "email": "wellness@apartment-leutasch.at",
    "url": "http://www.apartment-leutasch.at"
  },
  "name": "Haus am Burggraben",
  "image": [
    {
      "@type": "ImageObject",
      "url": "http://resc.deskline.net/images/SEE/1/cd4e9d64-9d22-49e8-a2f1-d8289b758f85/99/image.jpg",
      "caption": "Winter"
    },
    {
      "@type": "ImageObject",
      "url": "http://resc.deskline.net/images/SEE/1/253de2f5-e236-4690-9ef3-b89d3347916a/99/image.jpg",
      "caption": "Sommer"
    }
  ],
  "currenciesAccepted": "EUR",
  "makesOffer": [
    {
      "@type": "Offer",
      "name": "Appartement/Fewo, Dusche und Bad, WC, 2 Schlafräume",
      "availability": "http://schema.org/InStock",
      "itemOffered": [
        {
          "@type": [
            "Apartment",
            "Product"
          ],
          "name": "App. \"Enzian\", Dusche und Bad, WC, 2 Schlafräum",
          "numberOfRooms": "3.0",
          "occupancy": {
            "@type": "QuantitativeValue",
            "maxValue": "4",
            "minValue": "1"
          }
        }
      ],
      "priceSpecification": [
        {
          "@type": "PriceSpecification",
          "description": "Pax 1",
          "minPrice": "120.00",
          "maxPrice": "120.00",
          "priceCurrency": "EUR"
        },
        {
          "@type": "PriceSpecification",
          "description": "Pax 2",
          "minPrice": "120.00",
          "maxPrice": "120.00",
          "priceCurrency": "EUR"
        },
        {
          "@type": "PriceSpecification",
          "description": "Pax 3",
          "minPrice": "120.00",
          "maxPrice": "120.00",
          "priceCurrency": "EUR"
        },
        {
          "@type": "PriceSpecification",
          "description": "Pax 4",
          "minPrice": "130.00",
          "maxPrice": "130.00",
          "priceCurrency": "EUR"
        }
      ]
    },
    {
      "@type": "Offer",
      "name": "Appartement/Fewo, Dusche und Bad, WC, 2 Schlafräume",
      "availability": "http://schema.org/InStock",
      "itemOffered": [
        {
          "@type": [
            "Apartment",
            "Product"
          ],
          "name": "Edelweiß + Alpenrose, Du \u0026  Bad, WC, 2 Schlafräum",
          "numberOfRooms": "3.0",
          "occupancy": {
            "@type": "QuantitativeValue",
            "maxValue": "4",
            "minValue": "1"
          }
        }
      ],
      "priceSpecification": [
        {
          "@type": "PriceSpecification",
          "description": "Pax 1",
          "minPrice": "160.00",
          "maxPrice": "160.00",
          "priceCurrency": "EUR"
        },
        {
          "@type": "PriceSpecification",
          "description": "Pax 2",
          "minPrice": "160.00",
          "maxPrice": "160.00",
          "priceCurrency": "EUR"
        },
        {
          "@type": "PriceSpecification",
          "description": "Pax 3",
          "minPrice": "160.00",
          "maxPrice": "160.00",
          "priceCurrency": "EUR"
        },
        {
          "@type": "PriceSpecification",
          "description": "Pax 4",
          "minPrice": "170.00",
          "maxPrice": "170.00",
          "priceCurrency": "EUR"
        }
      ]
    }
  ]
}